{
  "last_updated": "2025-05-01T00:41:21.000Z",
  "activity": [
    {
      "type": "comment_created",
      "title": "beckn/use-case-gen-frontend#11",
      "time": "2025-05-01T00:41:21.000Z",
      "link": "https://github.com/beckn/use-case-gen-frontend/issues/11#issuecomment-2843809260",
      "text": "Hi @ravi-prakash-v  I would like to take this issue.\nI come with years of experience and hands on experience on open source projects.\nYou can check my Github Profile."
    },
    {
      "type": "comment_created",
      "title": "beckn/Unified-Energy-Interface#2",
      "time": "2025-05-01T00:40:17.000Z",
      "link": "https://github.com/beckn/Unified-Energy-Interface/issues/2#issuecomment-2843808105",
      "text": "Hi @ravi-prakash-v  I would like to take this issue.\nI come with years of experience and hands on experience on open source projects.\nYou can check my Github Profile."
    },
    {
      "type": "comment_created",
      "title": "beckn/protocol-specifications#313",
      "time": "2025-05-01T00:40:07.000Z",
      "link": "https://github.com/beckn/protocol-specifications/issues/313#issuecomment-2843807899",
      "text": "Hi @BLR-0118  I would like to take this issue.\nI come with years of experience and hands on experience on open source projects.\nYou can check my Github Profile."
    },
    {
      "type": "comment_created",
      "title": "beckn/protocol-specifications#321",
      "time": "2025-05-01T00:39:55.000Z",
      "link": "https://github.com/beckn/protocol-specifications/issues/321#issuecomment-2843807734",
      "text": "Hi @BLR-0118  I would like to take this issue.\nI come with years of experience and hands on experience on open source projects.\nYou can check my Github Profile."
    },
    {
      "type": "comment_created",
      "title": "beckn/trip-stitching-algorithm#1",
      "time": "2025-05-01T00:39:33.000Z",
      "link": "https://github.com/beckn/trip-stitching-algorithm/issues/1#issuecomment-2843807352",
      "text": "Hi @ravi-prakash-v  I would like to take this issue.\nI come with years of experience and hands on experience on open source projects.\nYou can check my Github Profile."
    },
    {
      "type": "comment_created",
      "title": "beckn/Unified-Energy-Interface#3",
      "time": "2025-05-01T00:35:48.000Z",
      "link": "https://github.com/beckn/Unified-Energy-Interface/issues/3#issuecomment-2843803230",
      "text": "Hi @ravi-prakash-v I would like to take this issue. \nI come with year of experience and hands on experience with open source projects.\nyou can check my github profile."
    },
    {
      "type": "comment_created",
      "title": "beckn/trip-stitching-algorithm#1",
      "time": "2025-05-01T00:15:24.000Z",
      "link": "https://github.com/beckn/trip-stitching-algorithm/issues/1#issuecomment-2843777402",
      "text": "Hi @ravi-prakash-v \n I would like to take this issue. I come with years of experience and hands on experience. You can check my profile: [Link](https://github.com/Itachii27)"
    }
  ],
  "open_prs": [],
  "authored_issue_and_pr": []
}